tempus/__init__.py
tempus/tempus.py
tempus/util.py
Tempus.py-1.1.0.dist-info/LICENSE
Tempus.py-1.1.0.dist-info/METADATA
Tempus.py-1.1.0.dist-info/WHEEL
Tempus.py-1.1.0.dist-info/top_level.txt
Tempus.py-1.1.0.dist-info/RECORD
