Metadata-Version: 2.1
Name: Tempus.py
Version: 1.1.0
Summary: Simple date handler
Home-page: https://github.com/yojona/tempus.py
Author: Jonathan Ayala
Author-email: yojona@msn.com
License: MIT
Platform: UNKNOWN
Classifier: License :: OSI Approved :: MIT License
Classifier: Programming Language :: Python :: 3
